ppatch-0.0.5.dist-info/METADATA
ppatch-0.0.5.dist-info/WHEEL
ppatch-0.0.5.dist-info/entry_points.txt
ppatch-0.0.5.dist-info/licenses/LICENSE
ppatch/__init__.py
ppatch/__main__.py
ppatch/__version__.py
ppatch/app.py
ppatch/commands/apply.py
ppatch/commands/auto.py
ppatch/commands/cache.py
ppatch/commands/get.py
ppatch/commands/help.py
ppatch/commands/show.py
ppatch/commands/symbol.py
ppatch/commands/trace.py
ppatch/config.py
ppatch/model.py
ppatch/utils/common.py
ppatch/utils/parse.py
ppatch/utils/resolve.py
ppatch-0.0.5.dist-info/RECORD
