Metadata-Version: 2.1
Name: ppatch
Version: 0.0.5
Summary: Universal tool to analyze patches
Author-Email: jingfelix <jingfelix@outlook.com>
License: MIT
Requires-Python: >=3.10
Requires-Dist: typer[all]>=0.9.0
Requires-Dist: pydantic>=2.5.3
Requires-Dist: pydantic-settings>=2.2.1
Requires-Dist: cscopy>=0.0.3
Requires-Dist: whatthepatch-pydantic==1.0.6a2
